tool_box/__init__.py
tool_box/feishu.py
tool_box/rclone.py
tool_box/telegram.py
tool_box/tools.py
tool_box_951-2025.10.4.data/data/LICENSE
tool_box_951-2025.10.4.dist-info/LICENSE
tool_box_951-2025.10.4.dist-info/METADATA
tool_box_951-2025.10.4.dist-info/WHEEL
tool_box_951-2025.10.4.dist-info/top_level.txt
tool_box_951-2025.10.4.dist-info/RECORD
