Metadata-Version: 2.1
Name: tool-box-951
Version: 2025.10.4
Summary: sync tool: rclone
Author: Xin-Xin Ma
License: GPL
Project-URL: Source, https://gitee.com/SIZXSN6/zcfg
License-File: LICENSE
Requires-Dist: loguru
Requires-Dist: requests
